symtorch/__init__.py
symtorch/operations.py
symtorch/symbolic_module.py
symtorch/utils.py
symtorch-0.2.0.dist-info/METADATA
symtorch-0.2.0.dist-info/WHEEL
symtorch-0.2.0.dist-info/top_level.txt
symtorch-0.2.0.dist-info/RECORD
