Metadata-Version: 2.1
Name: symtorch
Version: 0.2.0
Summary: Symbolic Expressions in PyTorch
Author-email: John Gardner <gardner.john97@gmail.com>
Project-URL: Homepage, https://github.com/jla-gardner/symtorch
Classifier: License :: OSI Approved :: MIT License
Classifier: Programming Language :: Python
Classifier: Programming Language :: Python :: 3
Requires-Python: >=3.8
Requires-Dist: torch
Requires-Dist: sympy
Requires-Dist: numpy
Provides-Extra: dev
Requires-Dist: bumpver; extra == "dev"
Requires-Dist: ruff; extra == "dev"
Provides-Extra: docs
Requires-Dist: sphinx; extra == "docs"
Requires-Dist: furo; extra == "docs"
Requires-Dist: nbsphinx; extra == "docs"
Requires-Dist: sphinxext-opengraph; extra == "docs"
Requires-Dist: sphinx-copybutton; extra == "docs"
Requires-Dist: sphinx-autodoc-typehints; extra == "docs"
Requires-Dist: sphinx-design; extra == "docs"
Requires-Dist: sphinx-codeautolink; extra == "docs"
Provides-Extra: publish
Requires-Dist: build; extra == "publish"
Requires-Dist: twine; extra == "publish"
Provides-Extra: test
Requires-Dist: pytest; extra == "test"
Requires-Dist: pytest-cov; extra == "test"
